fr_notices/__init__.py
fr_notices/navigation.py
fr_notices/tests/__init__.py
fr_notices/tests/navigation_tests.py
notice_comment/__init__.py
notice_comment/docket.py
notice_comment/models.py
notice_comment/tasks.py
notice_comment/urls.py
notice_comment/views.py
notice_comment/management/__init__.py
notice_comment/management/commands/__init__.py
notice_comment/management/commands/setup_cors.py
notice_comment/migrations/0001_initial.py
notice_comment/migrations/__init__.py
notice_comment/tests/__init__.py
notice_comment/tests/docket_tests.py
notice_comment/tests/tasks_tests.py
notice_comment/tests/views_tests.py
regulations/__init__.py
regulations/all_urls.py
regulations/apps.py
regulations/context.py
regulations/url_caches.py
regulations/urls.py
regulations/generator/__init__.py
regulations/generator/api_reader.py
regulations/generator/generator.py
regulations/generator/html_builder.py
regulations/generator/label.py
regulations/generator/link_flattener.py
regulations/generator/node_types.py
regulations/generator/notices.py
regulations/generator/section_url.py
regulations/generator/subterp.py
regulations/generator/title_parsing.py
regulations/generator/toc.py
regulations/generator/versions.py
regulations/generator/layers/__init__.py
regulations/generator/layers/base.py
regulations/generator/layers/defined.py
regulations/generator/layers/definitions.py
regulations/generator/layers/diff_applier.py
regulations/generator/layers/external_citation.py
regulations/generator/layers/footnotes.py
regulations/generator/layers/formatting.py
regulations/generator/layers/graphics.py
regulations/generator/layers/internal_citation.py
regulations/generator/layers/interpretations.py
regulations/generator/layers/key_terms.py
regulations/generator/layers/layers_applier.py
regulations/generator/layers/location_replace.py
regulations/generator/layers/meta.py
regulations/generator/layers/paragraph_markers.py
regulations-8.4.2.dist-info/METADATA
regulations-8.4.2.dist-info/RECORD
regulations-8.4.2.dist-info/WHEEL
regulations-8.4.2.dist-info/top_level.txt
