Metadata-Version: 2.1
Name: regulations
Version: 8.4.2
Summary: UNKNOWN
Home-page: UNKNOWN
License: UNKNOWN
Platform: UNKNOWN
Classifier: License :: Public Domain
Classifier: License :: CC0 1.0 Universal (CC0 1.0) Public Domain Dedication
Provides-Extra: notice_comment
Requires-Dist: cached-property
Requires-Dist: django (<1.12,>=1.8)
Requires-Dist: requests
Requires-Dist: six
Requires-Dist: futures; python_version < "3"
Requires-Dist: enum34; python_version < "3.4"
Provides-Extra: notice_comment
Requires-Dist: boto3; extra == 'notice_comment'
Requires-Dist: celery; extra == 'notice_comment'
Requires-Dist: requests-toolbelt; extra == 'notice_comment'
